LICENSE
MANIFEST.in
README.md
pyproject.toml
setup.py
tangos/__init__.py
tangos/cached_writer.py
tangos/config.py
tangos/log.py
tangos/query.py
tangos/temporary_halolist.py
tangos/tracking.py
tangos.egg-info/PKG-INFO
tangos.egg-info/SOURCES.txt
tangos.egg-info/dependency_links.txt
tangos.egg-info/entry_points.txt
tangos.egg-info/not-zip-safe
tangos.egg-info/requires.txt
tangos.egg-info/top_level.txt
tangos/core/__init__.py
tangos/core/creator.py
tangos/core/data_attribute_mapper.py
tangos/core/dictionary.py
tangos/core/extraction_patterns.py
tangos/core/halo.py
tangos/core/simulation.py
tangos/core/timestep.py
tangos/core/tracking.py
tangos/core/halo_data/__init__.py
tangos/core/halo_data/link.py
tangos/core/halo_data/property.py
tangos/examples/__init__.py
tangos/examples/mergers.py
tangos/input_handlers/__init__.py
tangos/input_handlers/ahf_trees.py
tangos/input_handlers/caterpillar.py
tangos/input_handlers/changa_bh.py
tangos/input_handlers/consistent_trees.py
tangos/input_handlers/eagle.py
tangos/input_handlers/finding.py
tangos/input_handlers/output_testing.py
tangos/input_handlers/pynbody.py
tangos/input_handlers/ramsesHOP.py
tangos/input_handlers/yt.py
tangos/input_handlers/halo_stat_files/__init__.py
tangos/input_handlers/halo_stat_files/translations.py
tangos/live_calculation/__init__.py
tangos/live_calculation/parser.py
tangos/live_calculation/query_masking.py
tangos/live_calculation/query_multivalue_folding.py
tangos/live_calculation/builtin_functions/__init__.py
tangos/live_calculation/builtin_functions/arithmetic.py
tangos/live_calculation/builtin_functions/array.py
tangos/live_calculation/builtin_functions/link.py
tangos/live_calculation/builtin_functions/reassembly.py
tangos/live_calculation/builtin_functions/search.py
tangos/parallel_tasks/__init__.py
tangos/parallel_tasks/accumulative_statistics.py
tangos/parallel_tasks/async_message.py
tangos/parallel_tasks/barrier.py
tangos/parallel_tasks/database.py
tangos/parallel_tasks/jobs.py
tangos/parallel_tasks/lock.py
tangos/parallel_tasks/message.py
tangos/parallel_tasks/remote_import.py
tangos/parallel_tasks/shared_set.py
tangos/parallel_tasks/testing.py
tangos/parallel_tasks/backends/__init__.py
