Metadata-Version: 2.1
Name: tangos
Version: 1.11.0
Summary: TANGOS, the agile numerical galaxy organisation system
Author: Andrew Pontzen
Author-email: a.pontzen@ucl.ac.uk
License: BSD
Classifier: Development Status :: 5 - Production/Stable
Classifier: Intended Audience :: Developers
Classifier: Intended Audience :: Science/Research
Classifier: Topic :: Scientific/Engineering :: Astronomy
Classifier: Programming Language :: Python
Classifier: Programming Language :: Python :: 3.11
Classifier: Programming Language :: Python :: 3.12
Classifier: Programming Language :: Python :: 3.13
Classifier: Programming Language :: Python :: 3.14
Classifier: License :: OSI Approved :: BSD License
Requires-Python: >=3.11
Provides-Extra: rmdbs
Provides-Extra: test
License-File: LICENSE
